satalign/__init__.py
satalign/ecc.py
satalign/lgm.py
satalign/lightglue/__init__.py
satalign/lightglue/aliked.py
satalign/lightglue/disk.py
satalign/lightglue/dog_hardnet.py
satalign/lightglue/lightglue.py
satalign/lightglue/sift.py
satalign/lightglue/superpoint.py
satalign/lightglue/utils.py
satalign/lightglue/viz2d.py
satalign/main.py
satalign/pcc.py
satalign/utils.py
satalign-0.1.16.dist-info/LICENSE
satalign-0.1.16.dist-info/METADATA
satalign-0.1.16.dist-info/WHEEL
satalign-0.1.16.dist-info/RECORD
