Metadata-Version: 2.1
Name: satalign
Version: 0.1.16
Summary: Methods for spatial alignment of satellite imagery
Home-page: https://github.com/csaybar/satalign
Author: Cesar Aybar
Author-email: cesar.aybar@uv.es
Requires-Python: >=3.10,<4.0
Classifier: Programming Language :: Python :: 3
Classifier: Programming Language :: Python :: 3.10
Classifier: Programming Language :: Python :: 3.11
Classifier: Programming Language :: Python :: 3.12
Provides-Extra: deep
Provides-Extra: pcc
Requires-Dist: kornia (>=0.7.2)
Requires-Dist: matplotlib (>=3.7.1)
Requires-Dist: numpy (>=1.26.4)
Requires-Dist: opencv-python (>=4.8.0.76)
Requires-Dist: packaging (>=24.1) ; extra == "deep"
Requires-Dist: pandas (>=2.0.3)
Requires-Dist: pycolmap (>=3.10.0) ; extra == "deep"
Requires-Dist: rasterio (>=1.3.10)
Requires-Dist: scikit-image (>=0.23.1) ; extra == "pcc"
Requires-Dist: torch (>=2.0.0) ; extra == "deep"
Requires-Dist: torchvision (>=0.19.0) ; extra == "deep"
Requires-Dist: xarray (>=2023.7.0)
Project-URL: Documentation, https://csaybar.github.io/satalign/
Project-URL: Repository, https://github.com/csaybar/satalign
